haystack_integrations/__init__.py
haystack_integrations/components/__init__.py
haystack_integrations/components/converters/__init__.py
haystack_integrations/components/converters/py.typed
haystack_integrations/components/converters/azure_doc_intelligence/__init__.py
haystack_integrations/components/converters/azure_doc_intelligence/converter.py
azure_doc_intelligence_haystack-1.0.0.dist-info/METADATA
azure_doc_intelligence_haystack-1.0.0.dist-info/WHEEL
azure_doc_intelligence_haystack-1.0.0.dist-info/licenses/LICENSE
azure_doc_intelligence_haystack-1.0.0.dist-info/RECORD
