Metadata-Version: 2.4
Name: azure-doc-intelligence-haystack
Version: 1.0.0
Summary: Haystack integration for Azure Document Intelligence
Project-URL: Documentation, https://github.com/deepset-ai/haystack-core-integrations/tree/main/integrations/azure_doc_intelligence#readme
Project-URL: Issues, https://github.com/deepset-ai/haystack-core-integrations/issues
Project-URL: Source, https://github.com/deepset-ai/haystack-core-integrations/tree/main/integrations/azure_doc_intelligence
Author-email: deepset GmbH <info@deepset.ai>
License-Expression: Apache-2.0
License-File: LICENSE
Keywords: Azure,Document Converter,Document Intelligence,Haystack,OCR,PDF
Classifier: Development Status :: 4 - Beta
Classifier: License :: OSI Approved :: Apache Software License
Classifier: Programming Language :: Python
Classifier: Programming Language :: Python :: 3.10
Classifier: Programming Language :: Python :: 3.11
Classifier: Programming Language :: Python :: 3.12
Classifier: Programming Language :: Python :: 3.13
Classifier: Programming Language :: Python :: Implementation :: CPython
Requires-Python: >=3.10
Requires-Dist: azure-ai-documentintelligence>=1.0.0
Requires-Dist: haystack-ai>=2.22.0
